opinionated/__init__.py
opinionated/core.py
opinionated/__pycache__/__init__.cpython-310.pyc
opinionated/__pycache__/__init__.cpython-37.pyc
opinionated/__pycache__/__init__.cpython-38.pyc
opinionated/__pycache__/__init__.cpython-39.pyc
opinionated/__pycache__/core.cpython-310.pyc
opinionated/__pycache__/core.cpython-37.pyc
opinionated/__pycache__/core.cpython-38.pyc
opinionated/__pycache__/core.cpython-39.pyc
opinionated/data/opinionated_fsc.mplstyle
opinionated/data/opinionated_j.mplstyle
opinionated/data/opinionated_m.mplstyle
opinionated/data/opinionated_rc.mplstyle
opinionated/data/opinionated_sg.mplstyle
opinionated/data/opinionated_tw.mplstyle
opinionated/data/opinions.mplstyle
opinionated/fonts/FiraSans-Black.ttf
opinionated/fonts/FiraSans-BlackItalic.ttf
opinionated/fonts/FiraSans-Bold.ttf
opinionated/fonts/FiraSans-BoldItalic.ttf
opinionated/fonts/FiraSans-ExtraBold.ttf
opinionated/fonts/FiraSans-ExtraBoldItalic.ttf
opinionated/fonts/FiraSans-ExtraLight.ttf
opinionated/fonts/FiraSans-ExtraLightItalic.ttf
opinionated/fonts/FiraSans-Italic.ttf
opinionated/fonts/FiraSans-Light.ttf
opinionated/fonts/FiraSans-LightItalic.ttf
opinionated/fonts/FiraSans-Medium.ttf
opinionated/fonts/FiraSans-MediumItalic.ttf
opinionated/fonts/FiraSans-Regular.ttf
opinionated/fonts/FiraSans-SemiBold.ttf
opinionated/fonts/FiraSans-SemiBoldItalic.ttf
opinionated/fonts/FiraSans-Thin.ttf
opinionated/fonts/FiraSans-ThinItalic.ttf
opinionated/fonts/FiraSansCondensed-Black.ttf
opinionated/fonts/FiraSansCondensed-BlackItalic.ttf
opinionated/fonts/FiraSansCondensed-Bold.ttf
opinionated/fonts/FiraSansCondensed-BoldItalic.ttf
opinionated/fonts/FiraSansCondensed-ExtraBold.ttf
opinionated/fonts/FiraSansCondensed-ExtraBoldItalic.ttf
opinionated/fonts/FiraSansCondensed-ExtraLight.ttf
opinionated/fonts/FiraSansCondensed-ExtraLightItalic.ttf
opinionated/fonts/FiraSansCondensed-Italic.ttf
opinionated/fonts/FiraSansCondensed-Light.ttf
opinionated/fonts/FiraSansCondensed-LightItalic.ttf
opinionated-0.0.3.0.dist-info/LICENSE.txt
opinionated-0.0.3.0.dist-info/METADATA
opinionated-0.0.3.0.dist-info/WHEEL
opinionated-0.0.3.0.dist-info/top_level.txt
opinionated-0.0.3.0.dist-info/RECORD
