Metadata-Version: 2.1
Name: opinionated
Version: 0.0.3.0
Summary: opinionated provides simple, clean stylesheets for plotting with matplotlib and seaborn.
Home-page: https://github.com/MNoichl/opinionated
Author: MNoichl
Author-email: noichlmax@hotmail.co.uk
License: MIT
Project-URL: Documentation, https://github.com/MNoichl/opinionated
Platform: any
Classifier: Development Status :: 4 - Beta
Classifier: Programming Language :: Python
License-File: LICENSE.txt
Requires-Dist: matplotlib
Requires-Dist: seaborn
Requires-Dist: requests
Requires-Dist: colormaps
Requires-Dist: fonttools
Requires-Dist: importlib-metadata ; python_version < "3.8"
Provides-Extra: testing
Requires-Dist: setuptools ; extra == 'testing'
Requires-Dist: pytest ; extra == 'testing'
Requires-Dist: pytest-cov ; extra == 'testing'
